netsuitesdk/__init__.py
netsuitesdk/connection.py
netsuitesdk/api/__init__.py
netsuitesdk/api/accounting_periods.py
netsuitesdk/api/accounts.py
netsuitesdk/api/base.py
netsuitesdk/api/classifications.py
netsuitesdk/api/credit_memos.py
netsuitesdk/api/currencies.py
netsuitesdk/api/custom_lists.py
netsuitesdk/api/custom_record_types.py
netsuitesdk/api/custom_records.py
netsuitesdk/api/customers.py
netsuitesdk/api/departments.py
netsuitesdk/api/employees.py
netsuitesdk/api/expense_categories.py
netsuitesdk/api/expense_reports.py
netsuitesdk/api/files.py
netsuitesdk/api/folders.py
netsuitesdk/api/invoices.py
netsuitesdk/api/journal_entries.py
netsuitesdk/api/locations.py
netsuitesdk/api/projects.py
netsuitesdk/api/subsidiaries.py
netsuitesdk/api/tax_groups.py
netsuitesdk/api/tax_items.py
netsuitesdk/api/terms.py
netsuitesdk/api/vendor_bills.py
netsuitesdk/api/vendor_credits.py
netsuitesdk/api/vendor_payments.py
netsuitesdk/api/vendors.py
netsuitesdk/internal/__init__.py
netsuitesdk/internal/client.py
netsuitesdk/internal/constants.py
netsuitesdk/internal/exceptions.py
netsuitesdk/internal/netsuite_types.py
netsuitesdk/internal/utils.py
netsuite_sdk_py-0.1.0.dist-info/LICENSE
netsuite_sdk_py-0.1.0.dist-info/METADATA
netsuite_sdk_py-0.1.0.dist-info/WHEEL
netsuite_sdk_py-0.1.0.dist-info/top_level.txt
netsuite_sdk_py-0.1.0.dist-info/RECORD
