Metadata-Version: 2.1
Name: netsuite-sdk-py
Version: 0.1.0
Summary: Python SDK for accessing the NetSuite SOAP webservice
Home-page: https://github.com/Precanto/py-netsuite-sdk
Author: Precanto
Author-email: sagar@precanto.com
License: MIT
Keywords: netsuite,api,python,sdk
Platform: UNKNOWN
Classifier: Topic :: Internet :: WWW/HTTP
Classifier: Intended Audience :: Developers
Classifier: License :: OSI Approved :: MIT License
Classifier: Programming Language :: Python :: 3
Classifier: Operating System :: OS Independent
Requires-Python: >=3.6
